selfcord/__init__.py
selfcord/bot.py
selfcord/api/__init__.py
selfcord/api/activity.py
selfcord/api/errors.py
selfcord/api/events.py
selfcord/api/gateway.py
selfcord/api/http.py
selfcord/api/ipc.py
selfcord/api/voice.py
selfcord/models/__init__.py
selfcord/models/assets.py
selfcord/models/channels.py
selfcord/models/event_models.py
selfcord/models/flags.py
selfcord/models/guild.py
selfcord/models/message.py
selfcord/models/permissions.py
selfcord/models/sessions.py
selfcord/models/users.py
selfcord/models/webhooks.py
selfcord/utils/Captcha.py
selfcord/utils/__init__.py
selfcord/utils/command.py
selfcord/utils/logging.py
selfcord_py-1.0.3.dist-info/licenses/LICENSE
selfcord_py-1.0.3.dist-info/METADATA
selfcord_py-1.0.3.dist-info/WHEEL
selfcord_py-1.0.3.dist-info/top_level.txt
selfcord_py-1.0.3.dist-info/RECORD
