Metadata-Version: 2.4
Name: selfcord.py
Version: 1.0.3
Summary: A Discord API wrapper designed for selfbots!
Home-page: https://github.com/Shell1010/Selfcord
Author: Shell
License: MIT
Keywords: selfbot,discord,discordapi,discordwrapper
License-File: LICENSE
Requires-Dist: aiohttp==3.8.5
Requires-Dist: aioconsole==0.3.3
Requires-Dist: websockets==10.1
Requires-Dist: ujson==5.7.0
Requires-Dist: aiofiles==0.8.0
Requires-Dist: requests==2.31.0
Requires-Dist: uvloop==0.17.0
Provides-Extra: voice
Requires-Dist: pynacl==1.5.0; extra == "voice"
Requires-Dist: opuslib==3.0.1; extra == "voice"
Provides-Extra: linux
Requires-Dist: uvloop==0.17.0; extra == "linux"
Provides-Extra: windows
Requires-Dist: winloop==0.1.0; extra == "windows"
Dynamic: author
Dynamic: description
Dynamic: description-content-type
Dynamic: home-page
Dynamic: keywords
Dynamic: license
Dynamic: license-file
Dynamic: provides-extra
Dynamic: requires-dist
Dynamic: summary
